<safrxml>
    <Generation>
        <Record>
            <XMLVERSION>3</XMLVERSION>
            <TYPE>View</TYPE>
            <PROGRAM>Workbench Version 4.21.1_RC13  (GillianHannington 2026-02-18 03:37)</PROGRAM>
            <FILENAME>RTC_22356_04_SUBSTR_ALPHA_FROM_PRIOR_COLUMN[10818].xml</FILENAME>
            <CREATEDTIMESTAMP>2026-03-05 15:45:27</CREATEDTIMESTAMP>
            <CREATEDUSERID>GILLIAN</CREATEDUSERID>
        </Record>
    </Generation>
    <View>
        <Record>
            <ENVIRONID>615</ENVIRONID>
            <VIEWID>10818</VIEWID>
            <NAME>RTC_22356_04_SUBSTR_ALPHA_FROM_PRIOR_COLUMN</NAME>
            <EFFDATE></EFFDATE>
            <VIEWSTATUSCD>ACTVE</VIEWSTATUSCD>
            <VIEWTYPECD>DETL </VIEWTYPECD>
            <EXTRACTFILEPARTNBR>1</EXTRACTFILEPARTNBR>
            <OUTPUTMEDIACD>FILE </OUTPUTMEDIACD>
            <OUTPUTLRID></OUTPUTLRID>
            <LFPFASSOCID>0</LFPFASSOCID>
            <PAGESIZE>66</PAGESIZE>
            <LINESIZE>250</LINESIZE>
            <ZEROSUPPRESSIND>0</ZEROSUPPRESSIND>
            <EXTRACTMAXRECCNT>0</EXTRACTMAXRECCNT>
            <EXTRACTSUMMARYIND>0</EXTRACTSUMMARYIND>
            <EXTRACTSUMMARYBUF>0</EXTRACTSUMMARYBUF>
            <OUTPUTMAXRECCNT>0</OUTPUTMAXRECCNT>
            <CONTROLRECID>1238</CONTROLRECID>
            <WRITEEXITID></WRITEEXITID>
            <WRITEEXITSTARTUP></WRITEEXITSTARTUP>
            <FORMATEXITID></FORMATEXITID>
            <FORMATEXITSTARTUP></FORMATEXITSTARTUP>
            <FILEFLDDELIMCD></FILEFLDDELIMCD>
            <FILESTRDELIMCD></FILESTRDELIMCD>
            <DELIMHEADERROWIND>0</DELIMHEADERROWIND>
            <FORMATFILTLOGIC><![CDATA[]]></FORMATFILTLOGIC>
            <COMMENTS></COMMENTS>
            <CREATEDTIMESTAMP>2022-01-21 07:37:07</CREATEDTIMESTAMP>
            <CREATEDUSERID>MSHAP   </CREATEDUSERID>
            <LASTMODTIMESTAMP>2026-03-04 23:26:44</LASTMODTIMESTAMP>
            <LASTMODUSERID>GILLIAN </LASTMODUSERID>
            <COMPILER>RCG: 4.1.0_RC21</COMPILER>
            <LASTACTTIMESTAMP>2026-03-05 01:44:08</LASTACTTIMESTAMP>
            <LASTACTUSERID>GILLIAN </LASTACTUSERID>
        </Record>
    </View>
    <View-Column>
        <Record>
            <ENVIRONID>615</ENVIRONID>
            <VIEWCOLUMNID>401944</VIEWCOLUMNID>
            <VIEWID>10818</VIEWID>
            <COLUMNNUMBER>1</COLUMNNUMBER>
            <FLDFMTCD>ALNUM</FLDFMTCD>
            <SIGNEDIND>0</SIGNEDIND>
            <STARTPOSITION>0</STARTPOSITION>
            <MAXLEN>256</MAXLEN>
            <ORDINALPOSITION>0</ORDINALPOSITION>
            <DECIMALCNT>0</DECIMALCNT>
            <ROUNDING>0</ROUNDING>
            <FLDCONTENTCD></FLDCONTENTCD>
            <JUSTIFYCD></JUSTIFYCD>
            <DEFAULTVAL></DEFAULTVAL>
            <VISIBLE>0</VISIBLE>
            <SUBTOTALTYPECD></SUBTOTALTYPECD>
            <SPACESBEFORECOLUMN>0</SPACESBEFORECOLUMN>
            <EXTRACTAREACD>AREDT</EXTRACTAREACD>
            <EXTRAREAPOSITION>1</EXTRAREAPOSITION>
            <SUBTLABEL></SUBTLABEL>
            <RPTMASK></RPTMASK>
            <HDRJUSTIFYCD></HDRJUSTIFYCD>
            <HDRLINE1>F1</HDRLINE1>
            <HDRLINE2></HDRLINE2>
            <HDRLINE3></HDRLINE3>
            <FORMATCALCLOGIC><![CDATA[]]></FORMATCALCLOGIC>
            <CREATEDTIMESTAMP>2022-01-21 07:39:35</CREATEDTIMESTAMP>
            <CREATEDUSERID>MSHAP   </CREATEDUSERID>
            <LASTMODTIMESTAMP>2022-01-21 07:39:35</LASTMODTIMESTAMP>
            <LASTMODUSERID>MSHAP   </LASTMODUSERID>
        </Record>
        <Record>
            <ENVIRONID>615</ENVIRONID>
            <VIEWCOLUMNID>401939</VIEWCOLUMNID>
            <VIEWID>10818</VIEWID>
            <COLUMNNUMBER>2</COLUMNNUMBER>
            <FLDFMTCD>ALNUM</FLDFMTCD>
            <SIGNEDIND>0</SIGNEDIND>
            <STARTPOSITION>1</STARTPOSITION>
            <MAXLEN>1</MAXLEN>
            <ORDINALPOSITION>1</ORDINALPOSITION>
            <DECIMALCNT>0</DECIMALCNT>
            <ROUNDING>0</ROUNDING>
            <FLDCONTENTCD></FLDCONTENTCD>
            <JUSTIFYCD></JUSTIFYCD>
            <DEFAULTVAL></DEFAULTVAL>
            <VISIBLE>1</VISIBLE>
            <SUBTOTALTYPECD></SUBTOTALTYPECD>
            <SPACESBEFORECOLUMN>0</SPACESBEFORECOLUMN>
            <EXTRACTAREACD>SORTK</EXTRACTAREACD>
            <EXTRAREAPOSITION>1</EXTRAREAPOSITION>
            <SUBTLABEL></SUBTLABEL>
            <RPTMASK></RPTMASK>
            <HDRJUSTIFYCD></HDRJUSTIFYCD>
            <HDRLINE1></HDRLINE1>
            <HDRLINE2></HDRLINE2>
            <HDRLINE3></HDRLINE3>
            <FORMATCALCLOGIC><![CDATA[]]></FORMATCALCLOGIC>
            <CREATEDTIMESTAMP>2022-01-21 07:37:07</CREATEDTIMESTAMP>
            <CREATEDUSERID>MSHAP   </CREATEDUSERID>
            <LASTMODTIMESTAMP>2022-01-21 07:39:36</LASTMODTIMESTAMP>
            <LASTMODUSERID>MSHAP   </LASTMODUSERID>
        </Record>
        <Record>
            <ENVIRONID>615</ENVIRONID>
            <VIEWCOLUMNID>401940</VIEWCOLUMNID>
            <VIEWID>10818</VIEWID>
            <COLUMNNUMBER>3</COLUMNNUMBER>
            <FLDFMTCD>ALNUM</FLDFMTCD>
            <SIGNEDIND>0</SIGNEDIND>
            <STARTPOSITION>2</STARTPOSITION>
            <MAXLEN>1</MAXLEN>
            <ORDINALPOSITION>2</ORDINALPOSITION>
            <DECIMALCNT>0</DECIMALCNT>
            <ROUNDING>0</ROUNDING>
            <FLDCONTENTCD></FLDCONTENTCD>
            <JUSTIFYCD></JUSTIFYCD>
            <DEFAULTVAL></DEFAULTVAL>
            <VISIBLE>1</VISIBLE>
            <SUBTOTALTYPECD></SUBTOTALTYPECD>
            <SPACESBEFORECOLUMN>0</SPACESBEFORECOLUMN>
            <EXTRACTAREACD>AREDT</EXTRACTAREACD>
            <EXTRAREAPOSITION>257</EXTRAREAPOSITION>
            <SUBTLABEL></SUBTLABEL>
            <RPTMASK></RPTMASK>
            <HDRJUSTIFYCD></HDRJUSTIFYCD>
            <HDRLINE1></HDRLINE1>
            <HDRLINE2></HDRLINE2>
            <HDRLINE3></HDRLINE3>
            <FORMATCALCLOGIC><![CDATA[]]></FORMATCALCLOGIC>
            <CREATEDTIMESTAMP>2022-01-21 07:37:07</CREATEDTIMESTAMP>
            <CREATEDUSERID>MSHAP   </CREATEDUSERID>
            <LASTMODTIMESTAMP>2022-01-21 07:39:36</LASTMODTIMESTAMP>
            <LASTMODUSERID>MSHAP   </LASTMODUSERID>
        </Record>
        <Record>
            <ENVIRONID>615</ENVIRONID>
            <VIEWCOLUMNID>401941</VIEWCOLUMNID>
            <VIEWID>10818</VIEWID>
            <COLUMNNUMBER>4</COLUMNNUMBER>
            <FLDFMTCD>ALNUM</FLDFMTCD>
            <SIGNEDIND>0</SIGNEDIND>
            <STARTPOSITION>3</STARTPOSITION>
            <MAXLEN>10</MAXLEN>
            <ORDINALPOSITION>3</ORDINALPOSITION>
            <DECIMALCNT>0</DECIMALCNT>
            <ROUNDING>0</ROUNDING>
            <FLDCONTENTCD></FLDCONTENTCD>
            <JUSTIFYCD></JUSTIFYCD>
            <DEFAULTVAL></DEFAULTVAL>
            <VISIBLE>1</VISIBLE>
            <SUBTOTALTYPECD></SUBTOTALTYPECD>
            <SPACESBEFORECOLUMN>0</SPACESBEFORECOLUMN>
            <EXTRACTAREACD>AREDT</EXTRACTAREACD>
            <EXTRAREAPOSITION>258</EXTRAREAPOSITION>
            <SUBTLABEL></SUBTLABEL>
            <RPTMASK></RPTMASK>
            <HDRJUSTIFYCD></HDRJUSTIFYCD>
            <HDRLINE1></HDRLINE1>
            <HDRLINE2></HDRLINE2>
            <HDRLINE3></HDRLINE3>
            <FORMATCALCLOGIC><![CDATA[]]></FORMATCALCLOGIC>
            <CREATEDTIMESTAMP>2022-01-21 07:37:07</CREATEDTIMESTAMP>
            <CREATEDUSERID>MSHAP   </CREATEDUSERID>
            <LASTMODTIMESTAMP>2022-01-21 07:39:36</LASTMODTIMESTAMP>
            <LASTMODUSERID>MSHAP   </LASTMODUSERID>
        </Record>
        <Record>
            <ENVIRONID>615</ENVIRONID>
            <VIEWCOLUMNID>401942</VIEWCOLUMNID>
            <VIEWID>10818</VIEWID>
            <COLUMNNUMBER>5</COLUMNNUMBER>
            <FLDFMTCD>ALNUM</FLDFMTCD>
            <SIGNEDIND>0</SIGNEDIND>
            <STARTPOSITION>13</STARTPOSITION>
            <MAXLEN>1</MAXLEN>
            <ORDINALPOSITION>4</ORDINALPOSITION>
            <DECIMALCNT>0</DECIMALCNT>
            <ROUNDING>0</ROUNDING>
            <FLDCONTENTCD></FLDCONTENTCD>
            <JUSTIFYCD></JUSTIFYCD>
            <DEFAULTVAL></DEFAULTVAL>
            <VISIBLE>1</VISIBLE>
            <SUBTOTALTYPECD></SUBTOTALTYPECD>
            <SPACESBEFORECOLUMN>0</SPACESBEFORECOLUMN>
            <EXTRACTAREACD>AREDT</EXTRACTAREACD>
            <EXTRAREAPOSITION>268</EXTRAREAPOSITION>
            <SUBTLABEL></SUBTLABEL>
            <RPTMASK></RPTMASK>
            <HDRJUSTIFYCD></HDRJUSTIFYCD>
            <HDRLINE1></HDRLINE1>
            <HDRLINE2></HDRLINE2>
            <HDRLINE3></HDRLINE3>
            <FORMATCALCLOGIC><![CDATA[]]></FORMATCALCLOGIC>
            <CREATEDTIMESTAMP>2022-01-21 07:37:07</CREATEDTIMESTAMP>
            <CREATEDUSERID>MSHAP   </CREATEDUSERID>
            <LASTMODTIMESTAMP>2022-01-21 07:39:36</LASTMODTIMESTAMP>
            <LASTMODUSERID>MSHAP   </LASTMODUSERID>
        </Record>
        <Record>
            <ENVIRONID>615</ENVIRONID>
            <VIEWCOLUMNID>401943</VIEWCOLUMNID>
            <VIEWID>10818</VIEWID>
            <COLUMNNUMBER>6</COLUMNNUMBER>
            <FLDFMTCD>ALNUM</FLDFMTCD>
            <SIGNEDIND>0</SIGNEDIND>
            <STARTPOSITION>14</STARTPOSITION>
            <MAXLEN>1</MAXLEN>
            <ORDINALPOSITION>5</ORDINALPOSITION>
            <DECIMALCNT>0</DECIMALCNT>
            <ROUNDING>0</ROUNDING>
            <FLDCONTENTCD></FLDCONTENTCD>
            <JUSTIFYCD></JUSTIFYCD>
            <DEFAULTVAL></DEFAULTVAL>
            <VISIBLE>1</VISIBLE>
            <SUBTOTALTYPECD></SUBTOTALTYPECD>
            <SPACESBEFORECOLUMN>0</SPACESBEFORECOLUMN>
            <EXTRACTAREACD>AREDT</EXTRACTAREACD>
            <EXTRAREAPOSITION>269</EXTRAREAPOSITION>
            <SUBTLABEL></SUBTLABEL>
            <RPTMASK></RPTMASK>
            <HDRJUSTIFYCD></HDRJUSTIFYCD>
            <HDRLINE1></HDRLINE1>
            <HDRLINE2></HDRLINE2>
            <HDRLINE3></HDRLINE3>
            <FORMATCALCLOGIC><![CDATA[]]></FORMATCALCLOGIC>
            <CREATEDTIMESTAMP>2022-01-21 07:37:07</CREATEDTIMESTAMP>
            <CREATEDUSERID>MSHAP   </CREATEDUSERID>
            <LASTMODTIMESTAMP>2022-01-21 07:39:36</LASTMODTIMESTAMP>
            <LASTMODUSERID>MSHAP   </LASTMODUSERID>
        </Record>
    </View-Column>
    <View-Source>
        <Record>
            <ENVIRONID>615</ENVIRONID>
            <VIEWSOURCEID>16063</VIEWSOURCEID>
            <VIEWID>10818</VIEWID>
            <SRCSEQNBR>1</SRCSEQNBR>
            <INLRLFASSOCID>6102</INLRLFASSOCID>
            <EXTRACTFILTLOGIC><![CDATA[]]></EXTRACTFILTLOGIC>
            <OUTLFPFASSOCID>0</OUTLFPFASSOCID>
            <WRITEEXITID>0</WRITEEXITID>
            <WRITEEXITPARM></WRITEEXITPARM>
            <EXTRACTOUTPUTIND>0</EXTRACTOUTPUTIND>
            <EXTRACTOUTPUTLOGIC><![CDATA[WRITE(SOURCE=VIEW,DEST=EXT=001)]]></EXTRACTOUTPUTLOGIC>
            <CREATEDTIMESTAMP>2022-01-21 07:37:07</CREATEDTIMESTAMP>
            <CREATEDUSERID>MSHAP   </CREATEDUSERID>
            <LASTMODTIMESTAMP>2022-01-21 07:37:07</LASTMODTIMESTAMP>
            <LASTMODUSERID>MSHAP   </LASTMODUSERID>
        </Record>
    </View-Source>
    <View-Column-Source>
        <Record>
            <ENVIRONID>615</ENVIRONID>
            <VIEWCOLUMNSOURCEID>650860</VIEWCOLUMNSOURCEID>
            <VIEWCOLUMNID>401939</VIEWCOLUMNID>
            <VIEWSOURCEID>16063</VIEWSOURCEID>
            <VIEWID>10818</VIEWID>
            <SOURCETYPEID>4</SOURCETYPEID>
            <CONSTVAL></CONSTVAL>
            <LOOKUPID>0</LOOKUPID>
            <LRFIELDID></LRFIELDID>
            <EFFDATEVALUE></EFFDATEVALUE>
            <EFFDATETYPE></EFFDATETYPE>
            <EFFDATELRFIELDID>0</EFFDATELRFIELDID>
            <SORTTITLELOOKUPID>0</SORTTITLELOOKUPID>
            <SORTTITLELRFIELDID>0</SORTTITLELRFIELDID>
            <EXTRACTCALCLOGIC><![CDATA[COLUMN = SUBSTR(COL.1,1,1)]]></EXTRACTCALCLOGIC>
            <CREATEDTIMESTAMP>2022-01-21 07:37:08</CREATEDTIMESTAMP>
            <CREATEDUSERID>MSHAP   </CREATEDUSERID>
            <LASTMODTIMESTAMP>2022-01-21 07:39:36</LASTMODTIMESTAMP>
            <LASTMODUSERID>MSHAP   </LASTMODUSERID>
        </Record>
        <Record>
            <ENVIRONID>615</ENVIRONID>
            <VIEWCOLUMNSOURCEID>650861</VIEWCOLUMNSOURCEID>
            <VIEWCOLUMNID>401940</VIEWCOLUMNID>
            <VIEWSOURCEID>16063</VIEWSOURCEID>
            <VIEWID>10818</VIEWID>
            <SOURCETYPEID>4</SOURCETYPEID>
            <CONSTVAL></CONSTVAL>
            <LOOKUPID>0</LOOKUPID>
            <LRFIELDID></LRFIELDID>
            <EFFDATEVALUE></EFFDATEVALUE>
            <EFFDATETYPE></EFFDATETYPE>
            <EFFDATELRFIELDID>0</EFFDATELRFIELDID>
            <SORTTITLELOOKUPID>0</SORTTITLELOOKUPID>
            <SORTTITLELRFIELDID>0</SORTTITLELRFIELDID>
            <EXTRACTCALCLOGIC><![CDATA[COLUMN = LEFT(COL.1,1)]]></EXTRACTCALCLOGIC>
            <CREATEDTIMESTAMP>2022-01-21 07:37:08</CREATEDTIMESTAMP>
            <CREATEDUSERID>MSHAP   </CREATEDUSERID>
            <LASTMODTIMESTAMP>2022-01-21 07:39:36</LASTMODTIMESTAMP>
            <LASTMODUSERID>MSHAP   </LASTMODUSERID>
        </Record>
        <Record>
            <ENVIRONID>615</ENVIRONID>
            <VIEWCOLUMNSOURCEID>650862</VIEWCOLUMNSOURCEID>
            <VIEWCOLUMNID>401941</VIEWCOLUMNID>
            <VIEWSOURCEID>16063</VIEWSOURCEID>
            <VIEWID>10818</VIEWID>
            <SOURCETYPEID>4</SOURCETYPEID>
            <CONSTVAL></CONSTVAL>
            <LOOKUPID>0</LOOKUPID>
            <LRFIELDID></LRFIELDID>
            <EFFDATEVALUE></EFFDATEVALUE>
            <EFFDATETYPE></EFFDATETYPE>
            <EFFDATELRFIELDID>0</EFFDATELRFIELDID>
            <SORTTITLELOOKUPID>0</SORTTITLELOOKUPID>
            <SORTTITLELRFIELDID>0</SORTTITLELRFIELDID>
            <EXTRACTCALCLOGIC><![CDATA[COLUMN = SUBSTR(COL.1,5,10)]]></EXTRACTCALCLOGIC>
            <CREATEDTIMESTAMP>2022-01-21 07:37:08</CREATEDTIMESTAMP>
            <CREATEDUSERID>MSHAP   </CREATEDUSERID>
            <LASTMODTIMESTAMP>2022-01-21 07:39:36</LASTMODTIMESTAMP>
            <LASTMODUSERID>MSHAP   </LASTMODUSERID>
        </Record>
        <Record>
            <ENVIRONID>615</ENVIRONID>
            <VIEWCOLUMNSOURCEID>650863</VIEWCOLUMNSOURCEID>
            <VIEWCOLUMNID>401942</VIEWCOLUMNID>
            <VIEWSOURCEID>16063</VIEWSOURCEID>
            <VIEWID>10818</VIEWID>
            <SOURCETYPEID>4</SOURCETYPEID>
            <CONSTVAL></CONSTVAL>
            <LOOKUPID>0</LOOKUPID>
            <LRFIELDID></LRFIELDID>
            <EFFDATEVALUE></EFFDATEVALUE>
            <EFFDATETYPE></EFFDATETYPE>
            <EFFDATELRFIELDID>0</EFFDATELRFIELDID>
            <SORTTITLELOOKUPID>0</SORTTITLELOOKUPID>
            <SORTTITLELRFIELDID>0</SORTTITLELRFIELDID>
            <EXTRACTCALCLOGIC><![CDATA[COLUMN = SUBSTR(COL.1,256,1)]]></EXTRACTCALCLOGIC>
            <CREATEDTIMESTAMP>2022-01-21 07:37:08</CREATEDTIMESTAMP>
            <CREATEDUSERID>MSHAP   </CREATEDUSERID>
            <LASTMODTIMESTAMP>2022-01-21 07:39:36</LASTMODTIMESTAMP>
            <LASTMODUSERID>MSHAP   </LASTMODUSERID>
        </Record>
        <Record>
            <ENVIRONID>615</ENVIRONID>
            <VIEWCOLUMNSOURCEID>650864</VIEWCOLUMNSOURCEID>
            <VIEWCOLUMNID>401943</VIEWCOLUMNID>
            <VIEWSOURCEID>16063</VIEWSOURCEID>
            <VIEWID>10818</VIEWID>
            <SOURCETYPEID>4</SOURCETYPEID>
            <CONSTVAL></CONSTVAL>
            <LOOKUPID>0</LOOKUPID>
            <LRFIELDID></LRFIELDID>
            <EFFDATEVALUE></EFFDATEVALUE>
            <EFFDATETYPE></EFFDATETYPE>
            <EFFDATELRFIELDID>0</EFFDATELRFIELDID>
            <SORTTITLELOOKUPID>0</SORTTITLELOOKUPID>
            <SORTTITLELRFIELDID>0</SORTTITLELRFIELDID>
            <EXTRACTCALCLOGIC><![CDATA[COLUMN = RIGHT(COL.1,1)]]></EXTRACTCALCLOGIC>
            <CREATEDTIMESTAMP>2022-01-21 07:37:08</CREATEDTIMESTAMP>
            <CREATEDUSERID>MSHAP   </CREATEDUSERID>
            <LASTMODTIMESTAMP>2022-01-21 07:39:36</LASTMODTIMESTAMP>
            <LASTMODUSERID>MSHAP   </LASTMODUSERID>
        </Record>
        <Record>
            <ENVIRONID>615</ENVIRONID>
            <VIEWCOLUMNSOURCEID>650865</VIEWCOLUMNSOURCEID>
            <VIEWCOLUMNID>401944</VIEWCOLUMNID>
            <VIEWSOURCEID>16063</VIEWSOURCEID>
            <VIEWID>10818</VIEWID>
            <SOURCETYPEID>3</SOURCETYPEID>
            <CONSTVAL></CONSTVAL>
            <LOOKUPID>0</LOOKUPID>
            <LRFIELDID>400699</LRFIELDID>
            <EFFDATEVALUE></EFFDATEVALUE>
            <EFFDATETYPE></EFFDATETYPE>
            <EFFDATELRFIELDID>0</EFFDATELRFIELDID>
            <SORTTITLELOOKUPID>0</SORTTITLELOOKUPID>
            <SORTTITLELRFIELDID>0</SORTTITLELRFIELDID>
            <EXTRACTCALCLOGIC><![CDATA[COLUMN = {F1}]]></EXTRACTCALCLOGIC>
            <CREATEDTIMESTAMP>2022-01-21 07:39:36</CREATEDTIMESTAMP>
            <CREATEDUSERID>MSHAP   </CREATEDUSERID>
            <LASTMODTIMESTAMP>2022-01-21 07:39:36</LASTMODTIMESTAMP>
            <LASTMODUSERID>MSHAP   </LASTMODUSERID>
        </Record>
    </View-Column-Source>
    <View-SortKey>
        <Record>
            <ENVIRONID>615</ENVIRONID>
            <VIEWSORTKEYID>41337</VIEWSORTKEYID>
            <VIEWID>10818</VIEWID>
            <VIEWCOLUMNID>401939</VIEWCOLUMNID>
            <KEYSEQNBR>1</KEYSEQNBR>
            <SORTSEQCD>ASCND</SORTSEQCD>
            <SORTBRKIND>1</SORTBRKIND>
            <PAGEBRKIND>0</PAGEBRKIND>
            <SORTKEYDISPLAYCD></SORTKEYDISPLAYCD>
            <SORTKEYLABEL></SORTKEYLABEL>
            <SKFLDFMTCD>ALNUM</SKFLDFMTCD>
            <SKSIGNED>0</SKSIGNED>
            <SKSTARTPOS>1</SKSTARTPOS>
            <SKFLDLEN>1</SKFLDLEN>
            <SKDECIMALCNT>0</SKDECIMALCNT>
            <SKFLDCONTENTCD></SKFLDCONTENTCD>
            <SORTTITLELRFIELDID>0</SORTTITLELRFIELDID>
            <SORTTITLELENGTH>0</SORTTITLELENGTH>
            <CREATEDTIMESTAMP>2022-01-21 07:37:08</CREATEDTIMESTAMP>
            <CREATEDUSERID>MSHAP   </CREATEDUSERID>
            <LASTMODTIMESTAMP>2026-03-05 01:44:09</LASTMODTIMESTAMP>
            <LASTMODUSERID>GILLIAN </LASTMODUSERID>
        </Record>
    </View-SortKey>
    <LogicalRecord>
        <Record>
            <ENVIRONID>615</ENVIRONID>
            <LOGRECID>10255</LOGRECID>
            <NAME>I2235601</NAME>
            <LRTYPECD>FILE </LRTYPECD>
            <LRSTATUSCD>ACTVE</LRSTATUSCD>
            <LOOKUPEXITID>0</LOOKUPEXITID>
            <LOOKUPEXITSTARTUP></LOOKUPEXITSTARTUP>
            <COMMENTS></COMMENTS>
            <CREATEDTIMESTAMP>2021-07-08 08:02:42</CREATEDTIMESTAMP>
            <CREATEDUSERID>MSHAP   </CREATEDUSERID>
            <LASTMODTIMESTAMP>2021-07-08 11:58:38</LASTMODTIMESTAMP>
            <LASTMODUSERID>MSHAP   </LASTMODUSERID>
            <LASTACTTIMESTAMP>2021-07-08 08:02:42</LASTACTTIMESTAMP>
            <LASTACTUSERID>MSHAP   </LASTACTUSERID>
        </Record>
    </LogicalRecord>
    <LRField>
        <Record>
            <ENVIRONID>615</ENVIRONID>
            <LRFIELDID>400699</LRFIELDID>
            <LOGRECID>10255</LOGRECID>
            <NAME>F1</NAME>
            <DBMSCOLNAME></DBMSCOLNAME>
            <FIXEDSTARTPOS>1</FIXEDSTARTPOS>
            <ORDINALPOS>1</ORDINALPOS>
            <ORDINALOFFSET></ORDINALOFFSET>
            <REDEFINE>0</REDEFINE>
            <COMMENTS></COMMENTS>
            <CREATEDTIMESTAMP>2021-07-08 08:02:42</CREATEDTIMESTAMP>
            <CREATEDUSERID>MSHAP   </CREATEDUSERID>
            <LASTMODTIMESTAMP>2021-07-08 11:58:39</LASTMODTIMESTAMP>
            <LASTMODUSERID>MSHAP   </LASTMODUSERID>
        </Record>
        <Record>
            <ENVIRONID>615</ENVIRONID>
            <LRFIELDID>400702</LRFIELDID>
            <LOGRECID>10255</LOGRECID>
            <NAME>F1_POS01</NAME>
            <DBMSCOLNAME></DBMSCOLNAME>
            <FIXEDSTARTPOS>1</FIXEDSTARTPOS>
            <ORDINALPOS>2</ORDINALPOS>
            <ORDINALOFFSET></ORDINALOFFSET>
            <REDEFINE>400699</REDEFINE>
            <COMMENTS></COMMENTS>
            <CREATEDTIMESTAMP>2021-07-08 11:58:39</CREATEDTIMESTAMP>
            <CREATEDUSERID>MSHAP   </CREATEDUSERID>
            <LASTMODTIMESTAMP>2021-07-08 11:58:39</LASTMODTIMESTAMP>
            <LASTMODUSERID>MSHAP   </LASTMODUSERID>
        </Record>
    </LRField>
    <LR-Field-Attribute>
        <Record>
            <ENVIRONID>615</ENVIRONID>
            <LRFIELDID>400699</LRFIELDID>
            <FLDFMTCD>ALNUM</FLDFMTCD>
            <SIGNEDIND>0</SIGNEDIND>
            <MAXLEN>256</MAXLEN>
            <DECIMALCNT>0</DECIMALCNT>
            <ROUNDING>0</ROUNDING>
            <FLDCONTENTCD></FLDCONTENTCD>
            <JUSTIFYCD></JUSTIFYCD>
            <HDRJUSTIFYCD></HDRJUSTIFYCD>
            <HDRLINE1></HDRLINE1>
            <HDRLINE2></HDRLINE2>
            <HDRLINE3></HDRLINE3>
            <SUBTLABEL></SUBTLABEL>
            <SORTKEYLABEL></SORTKEYLABEL>
            <INPUTMASK></INPUTMASK>
            <CREATEDTIMESTAMP>2021-07-08 08:02:42</CREATEDTIMESTAMP>
            <CREATEDUSERID>MSHAP   </CREATEDUSERID>
            <LASTMODTIMESTAMP>2021-07-08 11:58:39</LASTMODTIMESTAMP>
            <LASTMODUSERID>MSHAP   </LASTMODUSERID>
        </Record>
        <Record>
            <ENVIRONID>615</ENVIRONID>
            <LRFIELDID>400702</LRFIELDID>
            <FLDFMTCD>ALNUM</FLDFMTCD>
            <SIGNEDIND>0</SIGNEDIND>
            <MAXLEN>1</MAXLEN>
            <DECIMALCNT>0</DECIMALCNT>
            <ROUNDING>0</ROUNDING>
            <FLDCONTENTCD></FLDCONTENTCD>
            <JUSTIFYCD></JUSTIFYCD>
            <HDRJUSTIFYCD></HDRJUSTIFYCD>
            <HDRLINE1></HDRLINE1>
            <HDRLINE2></HDRLINE2>
            <HDRLINE3></HDRLINE3>
            <SUBTLABEL></SUBTLABEL>
            <SORTKEYLABEL></SORTKEYLABEL>
            <INPUTMASK></INPUTMASK>
            <CREATEDTIMESTAMP>2021-07-08 11:58:39</CREATEDTIMESTAMP>
            <CREATEDUSERID>MSHAP   </CREATEDUSERID>
            <LASTMODTIMESTAMP>2021-07-08 11:58:39</LASTMODTIMESTAMP>
            <LASTMODUSERID>MSHAP   </LASTMODUSERID>
        </Record>
    </LR-Field-Attribute>
    <LR-LF-Association>
        <Record>
            <ENVIRONID>615</ENVIRONID>
            <LRLFASSOCID>6102</LRLFASSOCID>
            <LOGFILEID>10225</LOGFILEID>
            <LOGRECID>10255</LOGRECID>
            <CREATEDTIMESTAMP>2021-07-08 08:02:43</CREATEDTIMESTAMP>
            <CREATEDUSERID>MSHAP   </CREATEDUSERID>
            <LASTMODTIMESTAMP>2021-07-08 08:02:43</LASTMODTIMESTAMP>
            <LASTMODUSERID>MSHAP   </LASTMODUSERID>
        </Record>
    </LR-LF-Association>
    <LogicalFile>
        <Record>
            <ENVIRONID>615</ENVIRONID>
            <LOGFILEID>10225</LOGFILEID>
            <NAME>I2235601</NAME>
            <COMMENTS></COMMENTS>
            <CREATEDTIMESTAMP>2021-07-08 08:01:33</CREATEDTIMESTAMP>
            <CREATEDUSERID>MSHAP   </CREATEDUSERID>
            <LASTMODTIMESTAMP>2021-07-08 11:49:14</LASTMODTIMESTAMP>
            <LASTMODUSERID>MSHAP   </LASTMODUSERID>
        </Record>
    </LogicalFile>
    <LF-PF-Association>
        <Record>
            <ENVIRONID>615</ENVIRONID>
            <LFPFASSOCID>20268</LFPFASSOCID>
            <PHYFILEID>11989</PHYFILEID>
            <PARTSEQNBR>1</PARTSEQNBR>
            <LOGFILEID>10225</LOGFILEID>
            <CREATEDTIMESTAMP>2021-07-08 08:01:33</CREATEDTIMESTAMP>
            <CREATEDUSERID>MSHAP   </CREATEDUSERID>
            <LASTMODTIMESTAMP>2021-07-08 08:01:33</LASTMODTIMESTAMP>
            <LASTMODUSERID>MSHAP   </LASTMODUSERID>
        </Record>
    </LF-PF-Association>
    <PhysicalFile>
        <Record>
            <ENVIRONID>615</ENVIRONID>
            <PHYFILEID>11989</PHYFILEID>
            <NAME>I2235601</NAME>
            <FILETYPECD>DISK </FILETYPECD>
            <DISKFILETYPECD></DISKFILETYPECD>
            <ACCESSMETHODCD>SEQIN</ACCESSMETHODCD>
            <READEXITID></READEXITID>
            <READEXITSTARTUP></READEXITSTARTUP>
            <DDNAMEINPUT>I2235601</DDNAMEINPUT>
            <DSN></DSN>
            <MINRECLEN>0</MINRECLEN>
            <MAXRECLEN>0</MAXRECLEN>
            <DDNAMEOUTPUT>        </DDNAMEOUTPUT>
            <RECFM></RECFM>
            <LRECL>0</LRECL>
            <DBMSSUBSYS></DBMSSUBSYS>
            <DBMSSQL><![CDATA[]]></DBMSSQL>
            <DBMSTABLE></DBMSTABLE>
            <DBMSROWFMTCD></DBMSROWFMTCD>
            <DBMSINCLNULLSIND>0</DBMSINCLNULLSIND>
            <COMMENTS></COMMENTS>
            <CREATEDTIMESTAMP>2021-07-08 08:01:10</CREATEDTIMESTAMP>
            <CREATEDUSERID>MSHAP   </CREATEDUSERID>
            <LASTMODTIMESTAMP>2021-07-08 11:32:02</LASTMODTIMESTAMP>
            <LASTMODUSERID>MSHAP   </LASTMODUSERID>
        </Record>
    </PhysicalFile>
    <ControlRecord>
        <Record>
            <ENVIRONID>615</ENVIRONID>
            <CONTROLRECID>1238</CONTROLRECID>
            <NAME>ControlRecord2</NAME>
            <FIRSTMONTH>1</FIRSTMONTH>
            <LOWVALUE>1</LOWVALUE>
            <HIGHVALUE>12</HIGHVALUE>
            <COMMENTS>Created automatically during initialization</COMMENTS>
            <CREATEDTIMESTAMP>2026-03-04 23:25:19</CREATEDTIMESTAMP>
            <CREATEDUSERID>GILLIAN </CREATEDUSERID>
            <LASTMODTIMESTAMP>2026-03-04 23:25:19</LASTMODTIMESTAMP>
            <LASTMODUSERID>GILLIAN </LASTMODUSERID>
        </Record>
    </ControlRecord>
</safrxml>
